{
	"analyst_email": "40170722@live.napier.ac.uk",
	"analyst_name": "Nathan Mair",
	"created": "2018-02-23T02:27:36",
	"edges": [
		{
			"id": "a1s1",
			"source_id": "a1",
			"target_id": "s1"
		},
		{
			"id": "a2s1",
			"source_id": "a2",
			"target_id": "s1"
		}, 
		{
			"id": "a3s2",
			"source_id": "a3",
			"target_id": "s2"
		},
		{
			"id": "s2a5",
			"source_id": "s2",
			"target_id": "a5"
		},
		{
			"id": "s1a4",
			"source_id": "s1",
			"target_id": "a4"
		},
		{
			"id": "a4s2",
			"source_id": "a4",
			"target_id": "s2"
		}
	],
	"edited": "2018-02-23T02:27:36",
	"id": "94a975db-25ae-4d25-93cc-1c07c932e2f9",
	"metadata": {},
	"nodes": [
		{
			"id": "a1",
			"metadata": {},
			"sources": [],
			"text": "Every person is going to die",
			"type": "atom"
		},
		{
			"id": "a2",
			"metadata": {},
			"sources": [],
			"text": "You are a person",
			"type": "atom"
		},
		{
			"id": "a3",
			"metadata": {},
			"sources": [],
			"text": "If you are going to die then you should treasure every moment",
			"type": "atom"
		},
		{
			"id": "a4",
			"metadata": {},
			"sources": [],
			"text": "You are going to die",
			"type": "atom"
		},
		{
			"id": "a5",
			"metadata": {},
			"sources": [],
			"text": "You should treasure every moment",
			"type": "atom"
		},
		{
			"id": "s1",
			"name": "Default\nSupport",
			"type": "scheme"
		},
		{
			"id": "s2",
			"name": "Default\nSupport",
			"type": "scheme"
		}
	], 
    "resources": []
}